ipylangchat/__init__.py
ipylangchat/static/widget.css
ipylangchat/static/widget.js
ipylangchat-0.0.2.dist-info/METADATA
ipylangchat-0.0.2.dist-info/WHEEL
ipylangchat-0.0.2.dist-info/licenses/LICENSE
ipylangchat-0.0.2.dist-info/RECORD
