Metadata-Version: 2.3
Name: ipylangchat
Version: 0.0.2
Summary: Serverless chat UI Jupyter widget for langchain conversational AIs
Project-URL: Homepage, https://github.com/abdenlab/ipylangchat
Author-email: Nezar Abdennur <nabdennur@gmail.com>
License: MIT
License-File: LICENSE
Classifier: License :: OSI Approved :: MIT License
Classifier: Operating System :: OS Independent
Classifier: Programming Language :: Python :: 3
Requires-Dist: anywidget
Requires-Dist: langchain-core
Provides-Extra: dev
Requires-Dist: jupyterlab; extra == 'dev'
Requires-Dist: langchain; extra == 'dev'
Requires-Dist: langchain-chroma; extra == 'dev'
Requires-Dist: langchain-community; extra == 'dev'
Requires-Dist: langchain-huggingface; extra == 'dev'
Requires-Dist: langchain-openai; extra == 'dev'
Requires-Dist: langchain-text-splitters; extra == 'dev'
Requires-Dist: watchfiles; extra == 'dev'
